{
  "schemaVersion": "0.1.1",
  "title": "Chase Bliss Dark World",
  "displayName": "Dark World",
  "implementationVersion": "0",

  "device": {
    "displayName": "",
    "manufacturer": "Chase Bliss",
    "model": "Dark World Dual Channel Reverb",
    "version": ""
  },

  "receives": ["PROGRAM_CHANGE", "CONTROL_CHANGE"],
  "transmits": [],

  "controlChangeCommands": [
    {
      "controlChangeNumber": 14,
      "name": "Decay",
      "valueRange": { "min": 0, "max": 127 }
    },
    {
      "controlChangeNumber": 15,
      "name": "Mix",
      "valueRange": { "min": 0, "max": 127 }
    },
    {
      "controlChangeNumber": 16,
      "name": "Dwell",
      "valueRange": { "min": 0, "max": 127 }
    },
    {
      "controlChangeNumber": 17,
      "name": "Modify",
      "valueRange": { "min": 0, "max": 127 }
    },
    {
      "controlChangeNumber": 18,
      "name": "Tone",
      "valueRange": { "min": 0, "max": 127 }
    },
    {
      "controlChangeNumber": 19,
      "name": "Pre-Delay",
      "valueRange": { "min": 0, "max": 127 }
    },

    {
      "controlChangeNumber": 21,
      "name": "Dark Program Select",
      "valueRange": {
        "min": 1,
        "max": 3,
        "discreteValues": [
          { "value": 1, "name": "Left" },
          { "value": 2, "name": "Middle" },
          { "value": 3, "name": "Right" }
        ]
      }
    },
    {
      "controlChangeNumber": 22,
      "name": "Para Toggle Select",
      "valueRange": {
        "min": 1,
        "max": 3,
        "discreteValues": [
          { "value": 1, "name": "Left" },
          { "value": 2, "name": "Middle" },
          { "value": 3, "name": "Right" }
        ]
      }
    },
    {
      "controlChangeNumber": 23,
      "name": "World Program Select",
      "valueRange": {
        "min": 1,
        "max": 3,
        "discreteValues": [
          { "value": 1, "name": "Left" },
          { "value": 2, "name": "Middle" },
          { "value": 3, "name": "Right" }
        ]
      }
    },

    {
      "controlChangeNumber": 100,
      "name": "Expression",
      "valueRange": { "min": 0, "max": 127 }
    },

    {
      "controlChangeNumber": 102,
      "name": "Bypass Switch",
      "valueRange": {
        "min": 0,
        "max": 127,
        "discreteValues": [
          { "value": 0, "name": "Bypass" },
          { "value": 127, "name": "Engage (last saved state)" }
        ]
      }
    },
    {
      "controlChangeNumber": 103,
      "name": "Bypass Switch (Dark/World Channels)",
      "valueRange": {
        "min": 0,
        "max": 127,
        "discreteValues": [
          { "value": 0, "name": "Bypass D & W" },
          { "value": 45, "name": "World only" },
          { "value": 85, "name": "Dark only" },
          { "value": 127, "name": "Dark & World" }
        ]
      }
    }
  ],

  "x_pc": {
    "indexBase": 1,
    "count": 122,
    "bankSelect": "none"
  },

  "x_midiTrs": "TYPE_A",
  "x_midiChannel": 2
}
